cmerg/__init__.py
cmerg/erg.py
cmerg/version.py
cmerg-0.4.dist-info/METADATA
cmerg-0.4.dist-info/WHEEL
cmerg-0.4.dist-info/licenses/LICENSE
cmerg-0.4.dist-info/RECORD
