Metadata-Version: 2.4
Name: cmerg
Version: 0.4
Summary: Python parser for CarMaker ERG files.
Project-URL: Homepage, https://github.com/danielhrisca/cmerg
Author-email: Daniel Hrisca <daniel.hrisca@gmail.com>
License: MIT
License-File: LICENSE
Keywords: carmaker,development,erg
Classifier: Development Status :: 3 - Alpha
Classifier: License :: OSI Approved :: MIT License
Classifier: Operating System :: OS Independent
Classifier: Programming Language :: Python :: 3
Requires-Python: >=3.6
Requires-Dist: asammdf
Requires-Dist: numpy
